{
  "object_type": "CINEMATICUM_REAL_CASE_AUTHORITY_OBJECT_SLOT_INDEX",
  "schema_version": "cinematicum.real_case_authority_object_slot_index.v1",
  "institution": "CINEMATICUM",
  "root_sentence": "CINEMATICUM issues admissible motion pictures.",
  "case_id": "CASE_001_THE_LAST_RENDER",
  "current_state": "OUTSIDER_REPLAY_BUNDLE_LAW_DECLARED",
  "surface_type": "CASE_RECORD",
  "slot_index_scope": "REAL_CASE_AUTHORITY_OBJECTS_ONLY",
  "open_real_case_authority_intake_required": true,
  "real_case_authority_intake_docket_required": true,
  "real_case_authority_intake_open": true,
  "authority_object_admission_requests_allowed": true,
  "authority_object_slot_count": 8,
  "unfilled_authority_object_slot_count": 8,
  "accepted_authority_object_count": 0,
  "instantiated_authority_object_count": 0,
  "authority_object_slots": [
    {
      "slot_number": 1,
      "slot_id": "director_final_cut_authority",
      "required_authority_object": "DIRECTOR_FINAL_CUT_AUTHORITY_OBJECT",
      "authority_function": "director_accepts_final_cut",
      "slot_status": "UNFILLED",
      "admission_request_present": false,
      "accepted_decision_present": false,
      "instantiated_authority_object_present": false
    },
    {
      "slot_number": 2,
      "slot_id": "editorial_timeline_authority",
      "required_authority_object": "EDITORIAL_TIMELINE_LOCK_AUTHORITY_OBJECT",
      "authority_function": "editor_locks_timeline",
      "slot_status": "UNFILLED",
      "admission_request_present": false,
      "accepted_decision_present": false,
      "instantiated_authority_object_present": false
    },
    {
      "slot_number": 3,
      "slot_id": "sound_final_mix_authority",
      "required_authority_object": "SOUND_FINAL_MIX_LOCK_AUTHORITY_OBJECT",
      "authority_function": "sound_department_locks_final_mix",
      "slot_status": "UNFILLED",
      "admission_request_present": false,
      "accepted_decision_present": false,
      "instantiated_authority_object_present": false
    },
    {
      "slot_number": 4,
      "slot_id": "color_grade_authority",
      "required_authority_object": "COLOR_GRADE_LOCK_AUTHORITY_OBJECT",
      "authority_function": "color_authority_locks_grade",
      "slot_status": "UNFILLED",
      "admission_request_present": false,
      "accepted_decision_present": false,
      "instantiated_authority_object_present": false
    },
    {
      "slot_number": 5,
      "slot_id": "release_delivery_authority",
      "required_authority_object": "RELEASE_DELIVERY_ARTIFACT_AUTHORITY_OBJECT",
      "authority_function": "release_authority_locks_delivery_artifacts",
      "slot_status": "UNFILLED",
      "admission_request_present": false,
      "accepted_decision_present": false,
      "instantiated_authority_object_present": false
    },
    {
      "slot_number": 6,
      "slot_id": "archival_proof_chain_authority",
      "required_authority_object": "ARCHIVAL_PROOF_CHAIN_AUTHORITY_OBJECT",
      "authority_function": "archivist_locks_proof_chain",
      "slot_status": "UNFILLED",
      "admission_request_present": false,
      "accepted_decision_present": false,
      "instantiated_authority_object_present": false
    },
    {
      "slot_number": 7,
      "slot_id": "outsider_replay_authority",
      "required_authority_object": "OUTSIDER_REPLAY_PASSAGE_AUTHORITY_OBJECT",
      "authority_function": "outsider_replay_passes",
      "slot_status": "UNFILLED",
      "admission_request_present": false,
      "accepted_decision_present": false,
      "instantiated_authority_object_present": false
    },
    {
      "slot_number": 8,
      "slot_id": "terminal_closure_authority",
      "required_authority_object": "TERMINAL_CLOSURE_AUTHORITY_OBJECT",
      "authority_function": "terminal_closure_is_sealed",
      "slot_status": "UNFILLED",
      "admission_request_present": false,
      "accepted_decision_present": false,
      "instantiated_authority_object_present": false
    }
  ],
  "slot_index_present": true,
  "slot_index_sealed": true,
  "object_is_non_star_seal": false,
  "object_is_negative_capability_seal": false,
  "slot_index_does_not_satisfy_authority": true,
  "slot_index_does_not_advance_state": true,
  "slot_index_does_not_issue_motion_picture": true,
  "slot_index_does_not_admit_media": true,
  "slot_index_does_not_create_release_candidate": true,
  "slot_index_does_not_reopen_current_snapshot": true,
  "slot_index_does_not_create_new_snapshot": true,
  "authority_satisfied": false,
  "may_advance_now": false,
  "release_candidate_ready": false,
  "issued": false,
  "media_present": false,
  "outsider_replay_passed": false
}
